README.md
setup.py
ediri_qovery/__init__.py
ediri_qovery/_inputs.py
ediri_qovery/_utilities.py
ediri_qovery/annotations_group.py
ediri_qovery/application.py
ediri_qovery/aws_credentials.py
ediri_qovery/cluster.py
ediri_qovery/container.py
ediri_qovery/container_registry.py
ediri_qovery/database.py
ediri_qovery/deployment.py
ediri_qovery/deployment_stage.py
ediri_qovery/environment.py
ediri_qovery/get_annotations_group.py
ediri_qovery/get_application.py
ediri_qovery/get_aws_credentials.py
ediri_qovery/get_cluster.py
ediri_qovery/get_container.py
ediri_qovery/get_container_registry.py
ediri_qovery/get_database.py
ediri_qovery/get_deployment.py
ediri_qovery/get_deployment_stage.py
ediri_qovery/get_environment.py
ediri_qovery/get_git_token.py
ediri_qovery/get_helm.py
ediri_qovery/get_helm_repository.py
ediri_qovery/get_job.py
ediri_qovery/get_labels_group.py
ediri_qovery/get_organization.py
ediri_qovery/get_project.py
ediri_qovery/get_scaleway_credentials.py
ediri_qovery/git_token.py
ediri_qovery/helm.py
ediri_qovery/helm_repository.py
ediri_qovery/job.py
ediri_qovery/labels_group.py
ediri_qovery/organization.py
ediri_qovery/outputs.py
ediri_qovery/project.py
ediri_qovery/provider.py
ediri_qovery/pulumi-plugin.json
ediri_qovery/py.typed
ediri_qovery/scaleway_credentials.py
ediri_qovery.egg-info/PKG-INFO
ediri_qovery.egg-info/SOURCES.txt
ediri_qovery.egg-info/dependency_links.txt
ediri_qovery.egg-info/not-zip-safe
ediri_qovery.egg-info/requires.txt
ediri_qovery.egg-info/top_level.txt
ediri_qovery/config/__init__.py
ediri_qovery/config/vars.py