Metadata-Version: 2.1
Name: ediri-qovery
Version: 0.41.0
Summary: A Pulumi package for creating and managing qovery cloud resources.
Home-page: https://www.pulumi.com
License: Apache-2.0
Project-URL: Repository, https://github.com/dirien/pulumi-qovery
Keywords: pulumi qovery category/cloud
Platform: UNKNOWN
Requires-Python: >=3.8
